cottontaildb_client/__init__.py
cottontaildb_client/__main__.py
cottontaildb_client/cottontail_pb2.py
cottontaildb_client/cottontail_pb2.pyi
cottontaildb_client/cottontail_pb2_grpc.py
cottontaildb_client/cottontaildb_cli.py
cottontaildb_client/cottontaildb_client.py
tests/__init__.py
tests/test_cottontaildb_client.py
cottontaildb_client-0.16.7.dist-info/LICENSE
cottontaildb_client-0.16.7.dist-info/METADATA
cottontaildb_client-0.16.7.dist-info/WHEEL
cottontaildb_client-0.16.7.dist-info/entry_points.txt
cottontaildb_client-0.16.7.dist-info/top_level.txt
cottontaildb_client-0.16.7.dist-info/RECORD
