Metadata-Version: 2.1
Name: cottontaildb-client
Version: 0.16.7
Summary: A Cottontail DB gRPC client.
Home-page: https://github.com/Spiess/cottontaildb-python-client
Author: Florian Spiess
Author-email: florian.spiess@unibas.ch
Project-URL: Bug Tracker, https://github.com/Spiess/cottontaildb-python-client/issues
Classifier: Programming Language :: Python :: 3
Classifier: License :: OSI Approved :: MIT License
Classifier: Operating System :: OS Independent
Requires-Python: >=3.8
License-File: LICENSE
Requires-Dist: grpcio
Requires-Dist: grpcio-tools
